smart_datastore_local/__init__.py
smart_datastore_local/smart_datastore.py
smart_datastore_local/smart_vectorstore.py
smart_datastore_local-0.1.2.dist-info/METADATA
smart_datastore_local-0.1.2.dist-info/WHEEL
smart_datastore_local-0.1.2.dist-info/top_level.txt
smart_datastore_local-0.1.2.dist-info/RECORD
