Metadata-Version: 2.4
Name: smart-datastore-local
Version: 0.1.2
Summary: PyPI Package for Circles smart-datastore-local Python
Home-page: https://github.com/circles-zone/smart-datastore-local-python-package
Author: Circles
Author-email: info@circlez.ai
Classifier: Programming Language :: Python :: 3
Classifier: Operating System :: OS Independent
Requires-Dist: python-sdk-remote
Requires-Dist: logger-local
Requires-Dist: database-infrastructure-local>=0.1.4
Requires-Dist: database-mysql-local>=0.1.2
Requires-Dist: database-postgresql-local>=0.1.1
Requires-Dist: database-redis-local>=0.1.3
Requires-Dist: opensearch-local>=0.0.8
Dynamic: author
Dynamic: author-email
Dynamic: classifier
Dynamic: description
Dynamic: description-content-type
Dynamic: home-page
Dynamic: requires-dist
Dynamic: summary
